<ns0:TEI xmlns:ns0="http://www.tei-c.org/ns/1.0" xmlns:ns1="http://www.w3.org/2001/XInclude" xml:lang="en">
   <ns0:teiHeader>
      <ns0:fileDesc>
         <ns0:titleStmt>
            <ns0:title>Contract for the sale of a house and related structures</ns0:title>
            <ns0:editor ref="#JP">Jonathan Prag</ns0:editor>
	<ns0:principal ref="#RDS">Randall Souza</ns0:principal>
            <ns0:funder>John Fell OUP Research Fund</ns0:funder>
            <ns0:funder><ns0:ref target="https://cordis.europa.eu/project/id/885040">ERC Advanced Grant no.885040</ns0:ref></ns0:funder>
            <ns0:respStmt>
               <ns0:name xml:id="RDS" ref="https://orcid.org/0000-0002-2725-7725">Randall Souza</ns0:name>
               <ns0:resp>original data collection, research and file creation</ns0:resp>
            </ns0:respStmt>
            <ns0:respStmt>
               <ns0:name xml:id="JP" ref="http://orcid.org/0000-0003-3819-8537">Jonathan Prag</ns0:name>
               <ns0:resp>Project direction and corpus editing</ns0:resp>
            </ns0:respStmt>
            <ns0:respStmt>
               <ns0:name xml:id="JCu" ref="http://orcid.org/0000-0002-6686-3728">James Cummings</ns0:name>
               <ns0:resp>original template creation</ns0:resp>
            </ns0:respStmt>
            <ns0:respStmt>
               <ns0:name xml:id="JCh">James Chartrand</ns0:name>
               <ns0:resp>site construction and encoding</ns0:resp>
            </ns0:respStmt>
            <ns0:respStmt>
               <ns0:name xml:id="SS" ref="https://orcid.org/0000-0003-3914-9569">Simona Stoyanova</ns0:name>
               <ns0:resp>standardisation of template and encoding</ns0:resp>
            </ns0:respStmt>
           </ns0:titleStmt>
         <ns0:publicationStmt>
            <ns0:authority>I.Sicily</ns0:authority>
            <ns0:idno type="filename">ISic030057</ns0:idno>
            <ns0:idno type="TM">698778</ns0:idno>
            <ns0:idno type="EDR">153131</ns0:idno>
            <ns0:idno type="EDH" />
            <ns0:idno type="EDCS">71000208</ns0:idno>
            <ns0:idno type="PHI">340012</ns0:idno>
            <ns0:idno type="URI">http://sicily.classics.ox.ac.uk/inscription/ISic030057</ns0:idno>
            <ns0:availability>
               <ns0:licence target="http://creativecommons.org/licenses/by/4.0/">Licensed under a Creative Commons-Attribution 4.0 licence</ns0:licence>
            </ns0:availability>
         </ns0:publicationStmt>
         <ns0:sourceDesc>
            <ns0:msDesc>
               <ns0:msIdentifier>
                  <ns0:country>Italy</ns0:country>
                  <ns0:region>Sicily</ns0:region>
                     <ns0:settlement>Ragusa</ns0:settlement>
                  <ns0:repository role="museum" ref="http://sicily.classics.ox.ac.uk/museum/091">Museo Archeologico Ibleo</ns0:repository>
                  <ns0:idno type="inventory" />
                  <ns0:altIdentifier>
                     <ns0:idno />
                  </ns0:altIdentifier>
                </ns0:msIdentifier>
               <ns0:msContents>
                  <ns0:textLang mainLang="grc">Ancient Greek</ns0:textLang>
               </ns0:msContents>
               <ns0:physDesc>
                  <ns0:objectDesc>
                     <ns0:supportDesc>
                        <ns0:support>
                           <ns0:p>A lead sheet intact on the right side, damaged on the top, left, and bottom sides. The measurements below do not reflect the addition of a fragment to the left of the text as proposed in Souza 2022 in ZPE.</ns0:p>
                           <ns0:material ana="#material.metal.lead" ref="http://www.eagle-network.eu/voc/material/lod/108.html">Lead</ns0:material>
                           <ns0:objectType ana="#object.lamina" ref="http://www.eagle-network.eu/voc/objtyp/lod/145.html">lamina</ns0:objectType>
                           <ns0:dimensions>
                              <ns0:height unit="cm">6.8</ns0:height>
                              <ns0:width unit="cm">8.5</ns0:width>
                              <ns0:depth unit="cm">0.1</ns0:depth>
                           </ns0:dimensions>
                        </ns0:support>
                        <ns0:condition ana="#condition.damaged" />
                     </ns0:supportDesc>
                     <ns0:layoutDesc>
                        <ns0:layout>
                           <ns0:p>The top of the sheet is damaged and the first line of text is not well preserved, but does appear to be the first line of the document. The right margin is entirely preserved. The bottom of the sheet is damaged but the final preserved line of text does appear to be the last line of the document. The left margin is unknown, and it is an open question how much text is lost on the left side (see below in commentary). The text wraps and several words are continued fron one line onto the next, breaking roughly between syllables (Lines 4, 5).</ns0:p>
                           <ns0:rs ana="#execution.engraved" ref="https://www.eagle-network.eu/voc/writing/lod/3.html">engraved</ns0:rs>
                           <ns0:damage ana="#text_condition.incomplete" />
                           </ns0:layout>
                     </ns0:layoutDesc>
                  </ns0:objectDesc>
                  <ns0:handDesc>
                     <ns0:handNote>
                        <ns0:p>Main text has lunate sigma with crossbar (like a lunate epsilon), two-bar upsilon (longer right stroke), square epsilon.</ns0:p>
                        <ns0:p>List of witnesses has potentially several different hands that are difficult to differentiate: several different two-bar upsilons appear. There is a two-bar upsilon with the longer stroke on the right, as in the main text (lines 9, 12); a variant of this with the short stroke intersecting the long one almost at the top of the hasta (line 8); a three-bar upsilon with the intersection near the top of the hasta (line 13); and a two-bar upsilon with the longer stroke on the left (lines 10, 11). The epsilons have different slants and proportions. There is one omicron as in the main text (line 7), and one odd squared omicron (line 12).</ns0:p>
                     </ns0:handNote>
                     <ns0:handNote n="hand1" xml:id="m1">
                        <ns0:dimensions type="letterHeight">
                           <ns0:height unit="mm" atLeast="2" atMost="2">2</ns0:height>
                        </ns0:dimensions>
                        <ns0:dimensions type="interlinear">
                           <ns0:height unit="mm" atLeast="2" atMost="2">not recorded</ns0:height>
                        </ns0:dimensions>
                     </ns0:handNote>
                  </ns0:handDesc>
               </ns0:physDesc>
               <ns0:history>
                  <ns0:origin>
                     <ns0:origPlace>
                        <ns0:placeName type="ancient" ref="https://pleiades.stoa.org/places/462126">Kamarina</ns0:placeName>
			<ns0:placeName type="modern" ref="http://sws.geonames.org/8063309">Kamarina</ns0:placeName>
                        <ns0:geo>36.8718784874, 14.4483234195</ns0:geo>
                     </ns0:origPlace>
                     <ns0:origDate datingMethod="#julian" notBefore-custom="-0250" notAfter-custom="-0201" evidence="lettering">ca. 250-200 BCE</ns0:origDate>
                  </ns0:origin>
                  <ns0:provenance type="found">Original discovery not recorded; first attested in the collection of Diego Ricotti Prina.</ns0:provenance>
                  <ns0:provenance type="observed" subtype="autopsied" resp="#RDS" when="2014-03-24">Souza, 2014.03.24 (not on display)</ns0:provenance>
                  <ns0:acquisition>Acquired by the Museo Archeologico Ibleo in 1983.</ns0:acquisition>
               </ns0:history>
               </ns0:msDesc>
         </ns0:sourceDesc>
      </ns0:fileDesc>
      <ns0:encodingDesc>
         <ns0:p>Encoded following the latest EpiDoc guidelines</ns0:p>
         <ns1:include href="../alists/ISicily-taxonomies.xml">
            <ns1:fallback>
               <ns0:p>Taxonomies for ISicily controlled values</ns0:p>
            </ns1:fallback>
         </ns1:include>
         <ns1:include href="../alists/charDecl.xml">
            <ns1:fallback>
               <ns0:p>ISicily glyphs authority list</ns0:p>
            </ns1:fallback>
         </ns1:include>
      </ns0:encodingDesc>
      <ns0:profileDesc>
         <ns0:calendarDesc>
            <ns0:calendar xml:id="julian">
               <ns0:p>Julian Calendar</ns0:p>
            </ns0:calendar>
         </ns0:calendarDesc>
         <ns0:langUsage>
            <ns0:language ident="en">English</ns0:language>
            <ns0:language ident="it">Italian</ns0:language>
            <ns0:language ident="grc">Ancient Greek</ns0:language>
            <ns0:language ident="la">Latin</ns0:language>
            <ns0:language ident="he">Hebrew</ns0:language>
            <ns0:language ident="phn">Phoenician</ns0:language>
            <ns0:language ident="xpu">Punic</ns0:language>
            <ns0:language ident="osc">Oscan</ns0:language>
            <ns0:language ident="xly">Elymian</ns0:language>
            <ns0:language ident="scx">Sikel</ns0:language>
            <ns0:language ident="sxc">Sikan</ns0:language>
         </ns0:langUsage>
         <ns0:textClass>
            <ns0:keywords scheme="http://www.eagle-network.eu/voc/typeins.html">
               <ns0:term ana="#function.legal.private.contract" ref="https://www.eagle-network.eu/voc/typeins/lod/375.html">Private contract</ns0:term>
              </ns0:keywords>
         </ns0:textClass>
      </ns0:profileDesc>
      <ns0:revisionDesc status="draft">
         <ns0:listChange>
            <ns0:change when="2022-03-31" who="#RDS">Randall Souza created the draft file from template</ns0:change>
            <ns0:change when="2023-06-21" who="#JP">minor editing</ns0:change>
         </ns0:listChange>
      </ns0:revisionDesc>
   </ns0:teiHeader>
   <ns0:facsimile>
      <ns0:surface />
   </ns0:facsimile>
   <ns0:text>
      <ns0:body>
         <ns0:div type="edition" xml:space="preserve" xml:lang="grc" resp="#RDS">
         <ns0:ab>
         <ns0:lb n="1" /><ns0:gap reason="lost" atMost="3" atLeast="2" unit="character" /><ns0:orig>&#921;&#935;</ns0:orig><ns0:gap reason="lost" extent="unknown" unit="character" /><ns0:orig>&#923;&#921;</ns0:orig><ns0:gap reason="lost" extent="unknown" unit="character" />
         <ns0:lb n="2" /><ns0:gap reason="lost" atMost="3" atLeast="2" unit="character" />&#945;&#961;&#967;&#959;&#962; <ns0:supplied reason="lost">&#7945;</ns0:supplied>&#947;&#949;&#955;&#972;&#967;&#959;&#965; &#7957;&#954;&#964;&#945; <ns0:expan><ns0:abbr>&#948;&#949;&#965;</ns0:abbr><ns0:ex>&#964;&#941;&#961;&#945;</ns0:ex></ns0:expan> &#959;&#7984;&#954;&#943;&#945;&#957; &#960;&#945;&#963;<ns0:unclear>&#964;</ns0:unclear><ns0:supplied reason="lost">&#940;</ns0:supplied>&#948;&#945;
         <ns0:lb n="3" /><ns0:gap reason="lost" atMost="3" atLeast="2" unit="character" /><ns0:supplied reason="lost">&#955;</ns0:supplied>&#945;&#973;&#961;&#945;&#953; &#964;&#959;&#8166; &#7977;&#961;&#945;&#954;&#955;&#941;&#959;&#962; &#954;&#945;&#8054; &#964;&#8048;&#962; &#945;&#8016;&#955;&#8048;&#962; &#7952;&#954; &#964;&#959;<ns0:unclear>&#8166;</ns0:unclear> <ns0:unclear>&#952;</ns0:unclear>&#945;&#955;<ns0:unclear>&#940;</ns0:unclear><ns0:supplied reason="lost">&#956;</ns0:supplied>&#956;&#959;&#965;
         <ns0:lb n="4" /><ns0:gap reason="lost" atMost="3" atLeast="2" unit="character" />&#957; &#954;&#945;&#8054; &#964;&#8056; &#966;&#961;&#8134;&#957; &#954;&#945;&#8054; &#964;&#8048;&#957; &#956;&#973;&#955;&#945;&#957; &#7988;&#948;&#953;&#959;&#957; &#954;&#945;&#8054; &#964;&#8048; <ns0:supplied reason="lost">&#952;</ns0:supplied>&#965;&#961;&#974;&#956;&#945;
         <ns0:lb n="5" break="no" /><ns0:supplied reason="lost">&#964;&#945;</ns0:supplied><ns0:gap reason="lost" atMost="3" atLeast="2" unit="character" /><ns0:orig>&#913;</ns0:orig> &#960;&#941;&#957;&#964;&#949; &#964;&#945;&#955;&#940;&#957;&#964;&#969;&#957; &#960;&#8048;&#961; &#916;&#953;&#954;&#945;&#953;&#945;&#947;&#972;&#961;&#945;&#962; &#964;&#8118;&#962; &#7944;&#957;<ns0:unclear>&#964;</ns0:unclear>&#940;&#955;
         <ns0:lb n="6" break="no" /><ns0:supplied reason="lost">&#955;&#959;&#965;</ns0:supplied> <ns0:unclear>&#967;</ns0:unclear>&#942;&#961;&#945;&#962; <ns0:orig><ns0:unclear>&#921;</ns0:unclear>&#1017;</ns0:orig><ns0:gap reason="lost" extent="unknown" unit="character" /> <ns0:space extent="unknown" unit="character" />
         <ns0:lb n="7" /><ns0:supplied reason="lost">&#916;&#953;&#959;&#947;</ns0:supplied>&#941;&#957;&#951;&#962; &#928;&#961;&#940;<ns0:gap reason="lost" extent="unknown" unit="character" /> <ns0:expan><ns0:abbr>&#948;</ns0:abbr><ns0:ex>&#949;&#954;&#940;&#964;&#945;</ns0:ex></ns0:expan> <ns0:expan><ns0:abbr>&#960;&#961;&#974;</ns0:abbr><ns0:ex>&#964;&#945;</ns0:ex></ns0:expan> <ns0:space extent="unknown" unit="character" />
         <ns0:lb n="8" /><ns0:supplied reason="lost">&#7977;&#961;&#945;</ns0:supplied><ns0:unclear>&#954;</ns0:unclear>&#955;&#949;&#943;&#948;&#945;<ns0:unclear>&#962;</ns0:unclear> <ns0:gap reason="lost" extent="unknown" unit="character" /> &#7957;&#954;&#964;&#945; <ns0:expan><ns0:abbr>&#948;&#949;&#965;</ns0:abbr><ns0:ex>&#964;&#941;&#961;&#945;</ns0:ex></ns0:expan> <ns0:space extent="unknown" unit="character" />
         <ns0:lb n="9" /><ns0:supplied reason="lost" cert="low">&#916;&#953;&#959;&#957;</ns0:supplied><ns0:unclear>&#959;</ns0:unclear>&#973;&#963;&#953;&#959;&#962; <ns0:orig><ns0:unclear>&#937;</ns0:unclear></ns0:orig><ns0:gap reason="lost" extent="unknown" unit="character" /> <ns0:expan><ns0:abbr>&#948;&#949;&#965;</ns0:abbr><ns0:ex>&#964;&#941;&#961;&#945;</ns0:ex></ns0:expan> <ns0:space extent="unknown" unit="character" />
         <ns0:lb n="10" /><ns0:gap reason="lost" atLeast="5" atMost="6" unit="character" /><ns0:gap reason="illegible" extent="1" unit="character" />&#959;&#962; &#917;&#8016;<ns0:unclear>&#969;</ns0:unclear><ns0:space extent="unknown" unit="character" />
         <ns0:lb n="11" /><ns0:gap reason="lost" extent="unknown" unit="character" /> <ns0:expan><ns0:abbr>&#948;&#949;&#965;</ns0:abbr><ns0:ex>&#964;&#941;&#961;&#945;</ns0:ex></ns0:expan> <ns0:space extent="unknown" unit="character" />
         <ns0:lb n="12" /><ns0:gap reason="lost" extent="unknown" unit="character" /> <ns0:expan><ns0:abbr>&#948;</ns0:abbr><ns0:ex>&#949;&#954;&#940;&#964;</ns0:ex><ns0:abbr>&#945;</ns0:abbr></ns0:expan> <ns0:expan><ns0:abbr>&#948;&#949;&#965;</ns0:abbr><ns0:ex>&#964;&#941;&#961;&#945;</ns0:ex></ns0:expan> <ns0:space extent="unknown" unit="character" />
         <ns0:lb n="13" /><ns0:gap reason="lost" extent="unknown" unit="character" /> <ns0:expan><ns0:abbr>&#7957;&#954;&#964;</ns0:abbr><ns0:ex>&#945;</ns0:ex></ns0:expan> <ns0:expan><ns0:abbr>&#948;&#949;&#965;</ns0:abbr><ns0:ex>&#964;&#941;&#961;&#945;</ns0:ex></ns0:expan> &#7970; &#948;&#949;&#954;&#940;&#964;&#945; &#960;&#961;&#974;&#964;&#945; <ns0:space extent="unknown" unit="character" />
         <ns0:lb n="14" /><ns0:gap reason="lost" extent="unknown" unit="character" /> <ns0:supplied reason="lost">&#948;&#949;&#954;</ns0:supplied>&#940;&#964;&#945; &#960;&#961;&#940;&#964;&#945; <ns0:space extent="unknown" unit="character" />
         <ns0:lb n="15" /><ns0:gap reason="lost" extent="unknown" unit="character" /><ns0:space extent="unknown" unit="character" />
         <ns0:lb n="16" /><ns0:gap reason="lost" extent="unknown" unit="character" /> <ns0:expan><ns0:abbr><ns0:supplied reason="lost">&#964;</ns0:supplied>&#961;&#943;</ns0:abbr><ns0:ex>&#964;&#945;</ns0:ex></ns0:expan> &#954;&#945;&#8054; &#948;&#949;&#954;&#940;&#964;<ns0:supplied reason="lost">&#945;</ns0:supplied> <ns0:space extent="unknown" unit="character" />
         <ns0:lb n="17" /><ns0:space quantity="1" unit="line" />
         </ns0:ab>
         </ns0:div>
         <ns0:div type="apparatus" resp="#RDS">
           <ns0:listApp>
              <ns0:app><ns0:note>Text from Souza 2022 in ZPE.</ns0:note></ns0:app>
              <ns0:app loc="Line 2"><ns0:note>Manganaro does not expand the phratry-tribe designations here or elsewhere in the text.</ns0:note></ns0:app>
              <ns0:app loc="Line 4"><ns0:note><ns0:supplied reason="lost">&#963;&#8058;</ns0:supplied>&#957;, M. and C.</ns0:note></ns0:app>
              <ns0:app loc="Line 13"><ns0:note>On the lamina, the letter in the final word that must be an omega or an alpha is rendered oddly with two vertical lines.</ns0:note></ns0:app>
              <ns0:app loc="Line 14"><ns0:note><ns0:expan><ns0:abbr>&#948;&#965;</ns0:abbr><ns0:ex>&#969;</ns0:ex></ns0:expan> &#948;<ns0:supplied reason="lost">&#949;</ns0:supplied>&#954;&#940;&#964;&#945;, C.; </ns0:note></ns0:app>
              <ns0:app loc="Line 15"><ns0:note>M. read <ns0:unclear>&#916;&#917;&#933;</ns0:unclear>; C. read <ns0:supplied reason="lost">&#7957;&#954;&#964;&#945;</ns0:supplied> <ns0:expan><ns0:abbr>&#948;&#949;&#965;</ns0:abbr><ns0:ex>&#964;&#941;&#961;&#945;</ns0:ex></ns0:expan>; I cannot detect the existence of letters on this line either by autopsy nor photography.</ns0:note></ns0:app>
              <ns0:app loc="Line 16"><ns0:note><ns0:supplied reason="lost">&#932;</ns0:supplied>&#929;&#921;&#922;&#913;&#921;&#916;&#917;&#922;&#913;&#932;<ns0:gap reason="illegible" extent="1" unit="character" />, M.; <ns0:expan><ns0:abbr>&#964;&#961;&#943;</ns0:abbr><ns0:ex>&#964;&#945;</ns0:ex></ns0:expan> &#954;&#945;&#953; <ns0:expan><ns0:abbr>&#948;&#949;&#954;&#940;&#964;</ns0:abbr><ns0:ex>&#945;</ns0:ex></ns0:expan>, C. and D.</ns0:note></ns0:app>
           </ns0:listApp>
         </ns0:div>
         <ns0:div type="translation" xml:lang="en" resp="#RDS">
            <ns0:p>When ??? was in office...--archos son of Hagelochos sixth (phratry)-second (tribe) bought a house, a portico...in the district of Herakles, and the courtyards from the inner room...and the well and the private mill and the doorways...for five talents from Dikaiagora the daughter of Antallos. [Guarantors:] Tenth (phratry)-first (tribe). Sixth (phratry)-second (tribe). Sixth (phratry)-second (tribe). Sixth (phratry)-second (tribe). Tenth (phratry)-second (tribe). Sixth (phratry)-second (tribe) or tenth (phratry)-first (tribe). Twelfth (phratry). Sixth (phratry)-second (tribe). Thirteenth (phratry).</ns0:p>
         </ns0:div>
         <ns0:div type="commentary">
            <ns0:p />
         </ns0:div>
         <ns0:div type="bibliography">
            <ns0:listBibl type="edition">
               <ns0:bibl type="bulletin" n="SEG">
               	<ns0:citedRange>39.1002</ns0:citedRange>
               	<ns0:ptr target="http://zotero.org/groups/382445/items/F2GG87EQ" />
               <ns0:ref target="https://biblio.inscriptiones.org/epig10000796">https://biblio.inscriptiones.org/epig10000796</ns0:ref></ns0:bibl>
	 	<ns0:bibl type="bulletin" n="BE">
      			<ns0:citedRange>1999.0645</ns0:citedRange>
			<ns0:ptr target="http://zotero.org/groups/382445/items/77P5MNIR" />
		<ns0:ref target="https://biblio.inscriptiones.org/epig10001282">https://biblio.inscriptiones.org/epig10001282</ns0:ref></ns0:bibl>
		 <ns0:bibl>
			<ns0:author>Manganaro</ns0:author>
			<ns0:date>1989</ns0:date>
			<ns0:citedRange>199 Kam. VII fig.2</ns0:citedRange>
			<ns0:ptr target="http://zotero.org/groups/382445/items/SIK4QJV4" />
		<ns0:ref target="https://biblio.inscriptiones.org/epig10002637">https://biblio.inscriptiones.org/epig10002637</ns0:ref></ns0:bibl>
		<ns0:bibl type="corpus" n="IGDS2">
                         <ns0:author>Dubois</ns0:author>
                         <ns0:date>2008</ns0:date>
			<ns0:citedRange>51</ns0:citedRange>
			<ns0:ptr target="http://zotero.org/groups/382445/items/SM2KDHZC" />
		<ns0:ref target="https://biblio.inscriptiones.org/epig10000160">https://biblio.inscriptiones.org/epig10000160</ns0:ref></ns0:bibl>
		<ns0:bibl>
			<ns0:author>Souza</ns0:author>
			<ns0:date>2022</ns0:date>
			<ns0:citedRange>72 no.1</ns0:citedRange>
			<ns0:ptr target="http://zotero.org/groups/382445/items/2RKAGTPR" />
		<ns0:ref target="https://biblio.inscriptiones.org/epig10002688">https://biblio.inscriptiones.org/epig10002688</ns0:ref></ns0:bibl>
             </ns0:listBibl>
            <ns0:listBibl type="discussion">
               <ns0:bibl />
            </ns0:listBibl>
         </ns0:div>
      </ns0:body>
   </ns0:text>
</ns0:TEI>