<ns0:TEI xmlns:ns0="http://www.tei-c.org/ns/1.0" xmlns:ns1="http://www.w3.org/2001/XInclude" xml:lang="en">
    <ns0:teiHeader>
        <ns0:fileDesc>
            <ns0:titleStmt>
                <ns0:title>ISic020242</ns0:title>
                <ns0:editor ref="#JP">Jonathan Prag</ns0:editor>
                <ns0:principal ref="#VM">Valentina Mignosa</ns0:principal>
                <ns0:funder>John Fell OUP Research Fund</ns0:funder>
                <ns0:funder><ns0:ref target="https://cordis.europa.eu/project/id/885040">ERC Advanced Grant no.885040</ns0:ref></ns0:funder>
                <ns0:respStmt>
                     <ns0:name xml:id="JP" ref="https://orcid.org/0000-0003-3819-8537">Jonathan Prag</ns0:name>
                     <ns0:resp>project direction, template development and general editor</ns0:resp>
                </ns0:respStmt>
                <ns0:respStmt>
                    <ns0:name xml:id="VM" ref="https://orcid.org/0000-0002-7122-2511">Valentina Mignosa</ns0:name>
                    <ns0:resp>original data collection and editing, encoding text in Epidoc</ns0:resp>
                </ns0:respStmt>
                <ns0:respStmt>
                    <ns0:name xml:id="SS" ref="https://orcid.org/0000-0003-3914-9569">Simona Stoyanova</ns0:name>
                    <ns0:resp>standardisation of template and tidying up encoding</ns0:resp>
                </ns0:respStmt>
            </ns0:titleStmt>
            <ns0:publicationStmt>
                <ns0:authority>I.Sicily</ns0:authority>
                <ns0:idno type="filename">ISic020242</ns0:idno>
                <ns0:idno type="TM" />
                <ns0:idno type="EDR" />
                <ns0:idno type="EDH" />
                <ns0:idno type="EDCS" />
                <ns0:idno type="PHI" />
                <ns0:idno type="URI">http://sicily.classics.ox.ac.uk/inscription/ISic020242</ns0:idno>
                <ns0:availability>
                    <ns0:licence target="http://creativecommons.org/licenses/by/4.0/">Licensed under a Creative Commons-Attribution 4.0 licence.</ns0:licence>
                </ns0:availability>
            </ns0:publicationStmt>
            <ns0:sourceDesc>
                <ns0:msDesc>
                    <ns0:msIdentifier>
                        <ns0:country>Italy</ns0:country>
                        <ns0:region>Sicily</ns0:region>
                        <ns0:settlement>Palermo</ns0:settlement>
                        <ns0:repository role="museum" ref="http://sicily.classics.ox.ac.uk/museum/064">Museo Archeologico Regionale Antonino Salinas</ns0:repository>
                        <ns0:idno type="inventory">54287</ns0:idno>
                        <ns0:altIdentifier>
                            <ns0:settlement />
                            <ns0:repository />
                            <ns0:idno type="old" />
                        </ns0:altIdentifier>
                    </ns0:msIdentifier>
                    <ns0:msContents>
                        <ns0:textLang mainLang="xly">Elymian<ns0:certainty locus="value" match="../@mainLang" assertedValue="grc"><ns0:desc>Ancient Greek</ns0:desc></ns0:certainty></ns0:textLang>
                    </ns0:msContents>
                    <ns0:physDesc>
                        <ns0:objectDesc>
                            <ns0:supportDesc>
                                <ns0:support>
                                    <ns0:p>Fragment of foot of a black-glaze kylix.</ns0:p>
                                    <ns0:material ana="#material.clay.fired" ref="https://www.eagle-network.eu/voc/material/lod/131.html">ceramic</ns0:material>
                                    <ns0:objectType ana="#object.vessel.kylix" ref="http://kerameikos.org/id/kylix">kylix</ns0:objectType> 
                                    <ns0:dimensions>
                                        <ns0:height unit="cm">1.3</ns0:height>
                                        <ns0:dim type="diameter" unit="cm">7</ns0:dim>
                                        <ns0:width unit="cm" />
                                        <ns0:depth unit="cm" />
                                    </ns0:dimensions>
                                </ns0:support>
                                <ns0:condition ana="#condition.fragment" />
                            </ns0:supportDesc>
                            <ns0:layoutDesc>
                                <ns0:layout>
                                    <ns0:rs ana="#execution.scratched" ref="https://www.eagle-network.eu/voc/writing/lod/9">scratched</ns0:rs>
                                    <ns0:p>The text is placed on the underside of the foot.</ns0:p>
                                    <ns0:damage ana="#text_condition.incomplete text_condition.legible" />
                                </ns0:layout>
                            </ns0:layoutDesc>
                        </ns0:objectDesc>
                        <ns0:handDesc>
                            <ns0:handNote>
                                
                                <ns0:locus from="line1" to="line1">Line 1</ns0:locus>
                                <ns0:dimensions type="letterHeight">
                                    <ns0:height unit="mm" atLeast="8" atMost="11">8-11</ns0:height>
                                </ns0:dimensions>
                            </ns0:handNote>
                        </ns0:handDesc>
                    </ns0:physDesc>
                    <ns0:history>
                        <ns0:origin>
                            <ns0:origPlace>
                                <ns0:placeName type="ancient" ref="https://pleiades.stoa.org/places/462487">Segesta</ns0:placeName>
                                <ns0:placeName type="modern" />
                                <ns0:geo>37.94171, 12.83649</ns0:geo>
                            </ns0:origPlace>
                            <ns0:origDate datingMethod="#julian" evidence="archaeological-context material-context lettering" notBefore-custom="-0500" notAfter-custom="-0480">500&#8212;480 BCE</ns0:origDate>
                        </ns0:origin>
                        <ns0:provenance type="found" subtype="discovered" from="1957" to="1977">Found during the excavations (from 1957 to 1977) by the Soprintendenza alle Antichit&#224; della Sicilia Occidentale in the area of Grotta Vanella, on the north-east slope of Monte Barbaro<ns0:geo>37.94240, 12.84509</ns0:geo>, 1.9km east of temple of Segesta.</ns0:provenance>
                        <ns0:provenance type="observed" subtype="autopsied" resp="#VM" when="2021-12-15">Mignosa 2021-12-15</ns0:provenance>
                        <ns0:acquisition />
                    </ns0:history>
                </ns0:msDesc>
            </ns0:sourceDesc>
        </ns0:fileDesc>
        <ns0:encodingDesc>
             <ns0:p>Encoded following the latest EpiDoc guidelines</ns0:p>
             <ns1:include href="../alists/ISicily-taxonomies.xml">
                 <ns1:fallback>
                     <ns0:p>Taxonomies for ISicily controlled values</ns0:p>
                 </ns1:fallback>
             </ns1:include>
	  <ns1:include href="../alists/charDecl.xml">
	     <ns1:fallback>
	       <ns0:p>ISicily glyphs authority list</ns0:p>
	     </ns1:fallback>
	   </ns1:include>
         </ns0:encodingDesc>
        <ns0:profileDesc>
            <ns0:calendarDesc>
                <ns0:calendar xml:id="julian">
                    <ns0:p>Julian Calendar</ns0:p>
                </ns0:calendar>
            </ns0:calendarDesc>
            <ns0:langUsage>
                <ns0:language ident="en">English</ns0:language> 
                <ns0:language ident="it">Italian</ns0:language> 
                <ns0:language ident="grc">Ancient Greek</ns0:language> 
                <ns0:language ident="la">Latin</ns0:language> 
                <ns0:language ident="he">Hebrew</ns0:language> 
                <ns0:language ident="phn">Phoenician</ns0:language>
                <ns0:language ident="xpu">Punic</ns0:language>
                <ns0:language ident="osc">Oscan</ns0:language> 
                <ns0:language ident="xly">Elymian</ns0:language> 
                <ns0:language ident="scx">Sikel</ns0:language>  
                <ns0:language ident="sxc">Sikan</ns0:language>  
            </ns0:langUsage>
            <ns0:textClass>
                <ns0:keywords scheme="http://www.eagle-network.eu/voc/typeins.html">
                    <ns0:term ana="#function.unknown" ref="https://www.eagle-network.eu/voc/typeins/lod/143.html">unknown</ns0:term>
                </ns0:keywords>
            </ns0:textClass>
        </ns0:profileDesc>
        <ns0:revisionDesc status="draft">
            <ns0:listChange>
                <ns0:change when="2020-10-05" who="#SS">Simona Stoyanova normalised Unicode</ns0:change>
                <ns0:change when="2020-10-08" who="#SS">Simona Stoyanova updated list of languages</ns0:change>
                <ns0:change when="2020-12-10" who="#VM">Valentina Mignosa added metadata, text</ns0:change>
            </ns0:listChange>
        </ns0:revisionDesc>
    </ns0:teiHeader>
    <ns0:facsimile>
        <ns0:surface type="front">
            <ns0:graphic n="screen" url="ISic020242_tiled.tif" height="3680px" width="5520px">
                <ns0:desc>I.Sicily with the permission of the Assessorato Regionale dei Beni Culturali e dell&#8217;Identit&#224; Siciliana - Dipartimento dei Beni Culturali e dell&#8217;Identit&#224; Siciliana</ns0:desc>
            </ns0:graphic>
            <ns0:graphic n="print" url="ISic020242.jpg" height="3680px" width="5520px">
                <ns0:desc>I.Sicily with the permission of the Assessorato Regionale dei Beni Culturali e dell&#8217;Identit&#224; Siciliana - Dipartimento dei Beni Culturali e dell&#8217;Identit&#224; Siciliana</ns0:desc>
            </ns0:graphic>
         </ns0:surface>
    </ns0:facsimile>
    <ns0:text>
        <ns0:body>
            <ns0:div type="edition" xml:space="preserve" xml:lang="xly-Grek"> 
                    <ns0:ab>
                        <ns0:lb n="1" /><ns0:gap reason="lost" extent="unknown" unit="character" />&#932;&#933;&#932;<ns0:gap reason="lost" extent="unknown" unit="character" />
                    </ns0:ab>
            </ns0:div>
            <ns0:div type="edition" xml:space="preserve" subtype="transliteration" xml:lang="xly-Latn">
                <ns0:ab />
            </ns0:div>
            <ns0:div type="apparatus">
                <ns0:listApp>
                    <ns0:app>
                        <ns0:note>Text after Agostiniani 1977 (IAS I)</ns0:note>
                    </ns0:app>
                </ns0:listApp>
            </ns0:div>
            <ns0:div type="translation" xml:lang="en">
                <ns0:p />
            </ns0:div>
            <ns0:div type="translation" xml:lang="it">
                <ns0:p />
            </ns0:div>
            <ns0:div type="commentary" xml:lang="en">
                <ns0:p />
            </ns0:div>
            <ns0:div type="bibliography">
                <ns0:listBibl type="edition">
                    <ns0:bibl type="corpus" n="IAS1">
                        <ns0:author>Agostiniani</ns0:author>
                        <ns0:date>1977</ns0:date>
                        <ns0:citedRange>242</ns0:citedRange>
                        <ns0:ptr target="http://zotero.org/groups/382445/items/QR2S9AJ9" />
                    <ns0:ref target="https://biblio.inscriptiones.org/epig10002201">https://biblio.inscriptiones.org/epig10002201</ns0:ref></ns0:bibl>
                    <ns0:bibl>
                        <ns0:author>Tusa</ns0:author>
                        <ns0:date>1968-1969</ns0:date>
                        <ns0:citedRange>no.8</ns0:citedRange>
                        <ns0:ptr target="http://zotero.org/groups/382445/items/IRHR25WV" />
                    <ns0:ref target="https://biblio.inscriptiones.org/epig10001530">https://biblio.inscriptiones.org/epig10001530</ns0:ref></ns0:bibl>
                </ns0:listBibl>
                <ns0:listBibl type="discussion">
                    <ns0:bibl />
                </ns0:listBibl>
            </ns0:div>
        </ns0:body>
    </ns0:text>
</ns0:TEI>